XOR_CheckSum/XOR_CheckSum_string.py
XOR_CheckSum/__init__.py
XOR_CheckSum_zsd-1.0.7.dist-info/DESCRIPTION.rst
XOR_CheckSum_zsd-1.0.7.dist-info/METADATA
XOR_CheckSum_zsd-1.0.7.dist-info/RECORD
XOR_CheckSum_zsd-1.0.7.dist-info/WHEEL
XOR_CheckSum_zsd-1.0.7.dist-info/metadata.json
XOR_CheckSum_zsd-1.0.7.dist-info/top_level.txt
