Metadata-Version: 2.0
Name: XOR-CheckSum-zsd
Version: 1.0.7
Summary: XOR_CheckSum tools
Home-page: https://github.com/zhangsheng377/XOR_CheckSum_zsd
Author: zhangsheng377
Author-email: 435878393@qq.com
License: MIT
Keywords: XOR checksum string zsd
Platform: UNKNOWN
Classifier: Programming Language :: Python
Classifier: Programming Language :: Python :: 2
Classifier: Programming Language :: Python :: 2.7
Classifier: Programming Language :: Python :: 3
Classifier: Programming Language :: Python :: 3.5
Classifier: Programming Language :: Python :: 3.6
